module_found/__init__.py
module_found/import_hook.py
module_found/lazy_object.py
module_found.pth
module_found-0.2.1.dist-info/LICENSE
module_found-0.2.1.dist-info/METADATA
module_found-0.2.1.dist-info/WHEEL
module_found-0.2.1.dist-info/RECORD
