Metadata-Version: 2.1
Name: module-found
Version: 0.2.1
Summary: Automatically create modules instead of failing with ModuleNotFound
Home-page: https://github.com/LiadOz/module-found
Author: Liad Oz
Author-email: liadozil@gmail.com
Requires-Python: >=3.8,<4.0
Classifier: License :: OSI Approved :: MIT License
Classifier: Programming Language :: Python :: 3
Classifier: Programming Language :: Python :: 3.8
Classifier: Programming Language :: Python :: 3.9
Classifier: Programming Language :: Python :: 3.10
Classifier: Programming Language :: Python :: 3.11
Classifier: Programming Language :: Python :: 3.12
Requires-Dist: openai (>=1.13.3,<2.0.0)
Project-URL: Repository, https://github.com/LiadOz/module-found
